sahaj/__init__.py
sahaj/cli.py
sahaj/helpers.py
sahaj/__pycache__/__init__.cpython-314.pyc
sahaj/__pycache__/cli.cpython-314.pyc
sahaj-0.3.0.dist-info/licenses/LICENSE
sahaj-0.3.0.dist-info/licenses/LICENSE.md
sahaj-0.3.0.dist-info/METADATA
sahaj-0.3.0.dist-info/WHEEL
sahaj-0.3.0.dist-info/entry_points.txt
sahaj-0.3.0.dist-info/top_level.txt
sahaj-0.3.0.dist-info/RECORD
